pyinstrument/__init__.py
pyinstrument/__main__.py
pyinstrument/context_manager.py
pyinstrument/frame.py
pyinstrument/frame_info.py
pyinstrument/frame_ops.py
pyinstrument/middleware.py
pyinstrument/processors.py
pyinstrument/profiler.py
pyinstrument/py.typed
pyinstrument/session.py
pyinstrument/stack_sampler.py
pyinstrument/typing.py
pyinstrument/util.py
pyinstrument/low_level/pyi_floatclock.c
pyinstrument/low_level/pyi_floatclock.h
pyinstrument/low_level/pyi_shared.h
pyinstrument/low_level/pyi_timing_thread.c
pyinstrument/low_level/pyi_timing_thread.h
pyinstrument/low_level/pyi_timing_thread_python.py
pyinstrument/low_level/stat_profile.c
pyinstrument/low_level/stat_profile.cpython-314-aarch64-linux-musl.so
pyinstrument/low_level/stat_profile.pyi
pyinstrument/low_level/stat_profile_python.py
pyinstrument/low_level/types.py
pyinstrument/magic/__init__.py
pyinstrument/magic/_utils.py
pyinstrument/magic/magic.py
pyinstrument/renderers/__init__.py
pyinstrument/renderers/base.py
pyinstrument/renderers/console.py
pyinstrument/renderers/html.py
pyinstrument/renderers/jsonrenderer.py
pyinstrument/renderers/pstatsrenderer.py
pyinstrument/renderers/session.py
pyinstrument/renderers/speedscope.py
pyinstrument/renderers/html_resources/app.css
pyinstrument/renderers/html_resources/app.js
pyinstrument/vendor/__init__.py
pyinstrument/vendor/appdirs.py
pyinstrument/vendor/decorator.py
pyinstrument/vendor/keypath.py
pyinstrument-5.1.2.dist-info/METADATA
pyinstrument-5.1.2.dist-info/WHEEL
pyinstrument-5.1.2.dist-info/entry_points.txt
pyinstrument-5.1.2.dist-info/top_level.txt
pyinstrument-5.1.2.dist-info/RECORD
pyinstrument-5.1.2.dist-info/licenses/LICENSE
