Metadata-Version: 2.4
Name: pyinstrument
Version: 5.1.2
Summary: Call stack profiler for Python. Shows you why your code is slow!
Home-page: https://github.com/joerick/pyinstrument
Author: Joe Rickerby
Author-email: joerick@mac.com
Keywords: profiling,profile,profiler,cpu,time,sampling
Classifier: Environment :: Console
Classifier: Environment :: Web Environment
Classifier: Intended Audience :: Developers
Classifier: License :: OSI Approved :: BSD License
Classifier: Operating System :: MacOS
Classifier: Operating System :: Microsoft :: Windows
Classifier: Operating System :: POSIX
Classifier: Topic :: Software Development :: Debuggers
Classifier: Topic :: Software Development :: Testing
Requires-Python: >=3.8
License-File: LICENSE
Provides-Extra: test
Requires-Dist: pytest; extra == "test"
Requires-Dist: flaky; extra == "test"
Requires-Dist: trio; extra == "test"
Requires-Dist: cffi>=1.17.0; extra == "test"
Requires-Dist: greenlet>=3; extra == "test"
Requires-Dist: pytest-asyncio==0.23.8; extra == "test"
Requires-Dist: ipython; extra == "test"
Provides-Extra: bin
Requires-Dist: click; extra == "bin"
Requires-Dist: nox; extra == "bin"
Provides-Extra: docs
Requires-Dist: sphinx==7.4.7; extra == "docs"
Requires-Dist: myst-parser==3.0.1; extra == "docs"
Requires-Dist: furo==2024.7.18; extra == "docs"
Requires-Dist: sphinxcontrib-programoutput==0.17; extra == "docs"
Requires-Dist: sphinx-autobuild==2024.4.16; extra == "docs"
Provides-Extra: examples
Requires-Dist: numpy; extra == "examples"
Requires-Dist: django; extra == "examples"
Requires-Dist: litestar; extra == "examples"
Provides-Extra: types
Requires-Dist: typing_extensions; extra == "types"
Dynamic: author
Dynamic: author-email
Dynamic: classifier
Dynamic: description
Dynamic: description-content-type
Dynamic: home-page
Dynamic: keywords
Dynamic: license-file
Dynamic: provides-extra
Dynamic: requires-python
Dynamic: summary
